{
  "modules": [
    {
      "slug": "services",
      "displayName": "Services",
      "useCaseName": "Understand offering",
      "description": "Provides information about main services",
      "isMainCTA": false,
      "mainCTASection": {
        "slug": "main-landing"
      },
      "pageSections": [
        {
          "slug": "services1"
        },
        {
          "slug": "services2"
        }
      ]
    },
    {
      "slug": "blog",
      "displayName": "Blog",
      "useCaseName": "View blog",
      "description": "Displays informal diary-style entries",
      "isMainCTA": false,
      "mainCTASection": {
        "slug": "main-landing"
      },
      "pageSections": [
        {
          "slug": "blog1"
        },
        {
          "slug": "blog-archive1"
        }
      ]
    },
    {
      "slug": "features",
      "displayName": "Features",
      "useCaseName": "View features",
      "description": "Provides information about main features of offering",
      "isMainCTA": false,
      "mainCTASection": {
        "slug": "main-landing"
      },
      "pageSections": [
        {
          "slug": "home2"
        }
      ]
    },
    {
      "slug": "benefits",
      "displayName": "Benefits",
      "useCaseName": "Understand offering",
      "description": "Displays main benefits of using offering",
      "isMainCTA": false,
      "mainCTASection": {
        "slug": "main-landing"
      },
      "pageSections": [
        {
          "slug": "home3"
        }
      ]
    },
    {
      "slug": "about",
      "displayName": "About",
      "useCaseName": "Learn about",
      "description": "Provides information related to the organisation",
      "isMainCTA": false,
      "mainCTASection": {
        "slug": "main-landing"
      },
      "pageSections": [
        {
          "slug": "about1"
        },
        {
          "slug": "home4"
        }
      ]
    },
    {
      "slug": "contact",
      "displayName": "Contact",
      "useCaseName": "Make contact",
      "description": "Encourages and facilitates making contact",
      "isMainCTA": true,
      "mainCTASection": {
        "slug": "main-landing"
      },
      "pageSections": [
        {
          "slug": "contact1"
        },
        {
          "slug": "home4"
        }
      ]
    }
  ]
}
